kcquant/__init__.py
kcquant/kcquant.py
kcquant-0.1.10.dist-info/WHEEL
kcquant-0.1.10.dist-info/METADATA
kcquant-0.1.10.dist-info/RECORD
