Metadata-Version: 2.1
Name: kcquant
Version: 0.1.10
Summary: Color quantization toolkit for exploratory data analysis of images.
Home-page: https://github.com/kbkus/kcquant
Keywords: color,color quantization,eda
Author: kbkus
Author-email: kacikus@gmail.com
Requires-Python: >=3.7.1,<4.0.0
Classifier: Programming Language :: Python :: 3
Classifier: Programming Language :: Python :: 3.8
Classifier: Programming Language :: Python :: 3.9
Requires-Dist: Pillow (>=8.1.2,<9.0.0)
Requires-Dist: imutils (>=0.5.4,<0.6.0)
Requires-Dist: matplotlib (>=3.3.4,<4.0.0)
Requires-Dist: numpy (>=1.20.1,<2.0.0)
Requires-Dist: opencv-python (>=4.5.1,<5.0.0)
Requires-Dist: pandas (>=1.2.2,<2.0.0)
Requires-Dist: sklearn (>=0.0,<0.1)
Project-URL: Repository, https://github.com/kbkus/kcquant
